<?xml version="1.0" encoding="UTF-8"?>
<beans xmlns="http://www.springframework.org/schema/beans" xmlns:xsi="http://www.w3.org/2001/XMLSchema-instance" xmlns:aop="http://www.springframework.org/schema/aop" xmlns:context="http://www.springframework.org/schema/context" xmlns:jdbc="http://www.springframework.org/schema/jdbc" xmlns:jee="http://www.springframework.org/schema/jee" xmlns:jms="http://www.springframework.org/schema/jms"
	xmlns:lang="http://www.springframework.org/schema/lang" xmlns:mvc="http://www.springframework.org/schema/mvc" xmlns:p="http://www.springframework.org/schema/p" xmlns:tx="http://www.springframework.org/schema/tx" xmlns:util="http://www.springframework.org/schema/util"
	xsi:schemaLocation="http://www.springframework.org/schema/beans http://www.springframework.org/schema/beans/spring-beans-3.0.xsd
		http://www.springframework.org/schema/aop http://www.springframework.org/schema/aop/spring-aop-3.0.xsd
		http://www.springframework.org/schema/context http://www.springframework.org/schema/context/spring-context-3.0.xsd
		http://www.springframework.org/schema/jdbc http://www.springframework.org/schema/jdbc/spring-jdbc-3.0.xsd
		http://www.springframework.org/schema/jee http://www.springframework.org/schema/jee/spring-jee-3.0.xsd
		http://www.springframework.org/schema/jms http://www.springframework.org/schema/jms/spring-jms-3.0.xsd
		http://www.springframework.org/schema/lang http://www.springframework.org/schema/lang/spring-lang-3.0.xsd
		http://www.springframework.org/schema/mvc http://www.springframework.org/schema/mvc/spring-mvc-3.0.xsd
		http://www.springframework.org/schema/tx http://www.springframework.org/schema/tx/spring-tx-3.0.xsd
		http://www.springframework.org/schema/util http://www.springframework.org/schema/util/spring-util-3.0.xsd">
	<bean id="fileCnf" class="tuxiazi.util.FileCnf">
		<property name="root_path" value="/home/tuxiazi/pub/pic/" />
		<property name="tmpPhotoPath" value="/home/tuxiazi/pub/tmppic/" />
		<property name="fileMaxSize" value="2" />
		<property name="directory" value="a/" />
		<property name="domain" value="http://www.tuxiazi.com/pic/" />
	</bean>
	<bean class="tuxiazi.util.PhotoUtil">
		<property name="fileCnf" ref="fileCnf" />
	</bean>
	<bean id="userService" class="tuxiazi.svr.impl.UserServiceImpl">
		<property name="api_user_sinaDao" ref="api_user_sinaDao" />
		<property name="api_userDao" ref="api_userDao" />
		<property name="userDao" ref="userDao" />
		<property name="useridDao" ref="useridDao" />
		<property name="invitelogService" ref="invitelogService" />
		<property name="hkMsgProducer" ref="hkMsgProducer" />
	</bean>
	<bean id="photoService" class="tuxiazi.svr.impl.PhotoServiceImpl">
		<property name="fileCnf" ref="fileCnf" />
		<property name="lasted_photo_max_count" value="20" />
	</bean>
	<bean id="friendService" class="tuxiazi.svr.impl.FriendServiceImpl" />
	<bean id="feedService" class="tuxiazi.svr.impl.FeedServiceImpl">
		<property name="maxSize" value="200" />
	</bean>
	<bean id="photoCmtService" class="tuxiazi.svr.impl.PhotoCmtServiceImpl" />
	<bean id="noticeService" class="tuxiazi.svr.impl.NoticeServiceImpl" />
	<bean id="invitelogService" class="tuxiazi.svr.impl.InvitelogServiceImpl" />
</beans>